Workbook

Sheet Pivot Table
F1: Product | G1: Sum of Units Sold
F2: Gaming Mouse | G2: 45
A3: Category | B3: Sum of Total Sales | F3: Bluetooth Speaker | G3: 43
A4: Accessories | B4: 613132 | F4: LED Monitor | G4: 40
A5: Computers | B5: 1264843 | F5: Backpack | G5: 38
A6: Electronics | B6: 844189 | F6: Phone Case | G6: 36
A7: Grand Total | B7: 2722164 | F7: Grand Total | G7: 202
A12: Customer Name2 | B12: Sum of Profit
A13: East | B13: 132245
A14: North | B14: 201273
A15: South | B15: 136912 | F15: Sales Channel | G15: Count of Order ID
A16: West | B16: 217839 | F16: Online | G16: 46
A17: Grand Total | B17: 688269 | F17: Retail Store | G17: 54
F18: Grand Total | G18: 100
A30: Order Months | B30: Sum of Total Sales
A31: January | B31: 226999
A32: February | B32: 288751
A33: March | B33: 610240
A34: April | B34: 736630
A35: May | B35: 336789
A36: June | B36: 522755
A37: Grand Total | B37: 2722164

Sheet Sales_Data
A1: Order ID | B1: Date | C1: Customer Name | D1: Customer Region | E1: Product | F1: Category | G1: Sales Channel | H1: Units Sold | I1: Unit Price | J1: Total Sales | K1: Cost Price | L1: Profit | M1: Order Months
A2: 1001 | B2: 45735 | C2: Customer 2 | D2: North | E2: Bluetooth Speaker | F2: Electronics | G2: Online | H2: 4 | I2: 4650 | J2: 18600 | K2: 15331 | L2: 3269 | M2: =TEXT(B2,"mmmm") -> March
A3: 1002 | B3: 45684 | C3: Customer 12 | D3: East | E3: Bluetooth Speaker | F3: Electronics | G3: Online | H3: 5 | I3: 6451 | J3: 32255 | K3: 25586 | L3: 6669 | M3: =TEXT(B3,"mmmm") -> January
A4: 1003 | B4: 45726 | C4: Customer 1 | D4: South | E4: Smartwatch | F4: Electronics | G4: Online | H4: 5 | I4: 12003 | J4: 60015 | K4: 38515 | L4: 21500 | M4: =TEXT(B4,"mmmm") -> March
A5: 1004 | B5: 45710 | C5: Customer 34 | D5: South | E5: LED Monitor | F5: Computers | G5: Online | H5: 2 | I5: 13343 | J5: 26686 | K5: 23930 | L5: 2756 | M5: =TEXT(B5,"mmmm") -> February
A6: 1005 | B6: 45762 | C6: Customer 3 | D6: North | E6: LED Monitor | F6: Computers | G6: Online | H6: 2 | I6: 16723 | J6: 33446 | K6: 21829 | L6: 11617 | M6: =TEXT(B6,"mmmm") -> April
A7: 1006 | B7: 45769 | C7: Customer 22 | D7: East | E7: Backpack | F7: Accessories | G7: Online | H7: 3 | I7: 2735 | J7: 8205 | K7: 5668 | L7: 2537 | M7: =TEXT(B7,"mmmm") -> April
A8: 1007 | B8: 45660 | C8: Customer 13 | D8: West | E8: Wireless Earbuds | F8: Electronics | G8: Retail Store | H8: 4 | I8: 4919 | J8: 19676 | K8: 13615 | L8: 6061 | M8: =TEXT(B8,"mmmm") -> January
A9: 1008 | B9: 45818 | C9: Customer 29 | D9: West | E9: Bluetooth Speaker | F9: Electronics | G9: Retail Store | H9: 1 | I9: 4264 | J9: 4264 | K9: 3636 | L9: 628 | M9: =TEXT(B9,"mmmm") -> June
A10: 1009 | B10: 45758 | C10: Customer 17 | D10: North | E10: LED Monitor | F10: Computers | G10: Online | H10: 4 | I10: 16447 | J10: 65788 | K10: 52329 | L10: 13459 | M10: =TEXT(B10,"mmmm") -> April
A11: 1010 | B11: 45833 | C11: Customer 34 | D11: North | E11: Laptop | F11: Computers | G11: Retail Store | H11: 3 | I11: 1796 | J11: 5388 | K11: 3515 | L11: 1873 | M11: =TEXT(B11,"mmmm") -> June
A12: 1011 | B12: 45824 | C12: Customer 5 | D12: West | E12: Bluetooth Speaker | F12: Electronics | G12: Online | H12: 4 | I12: 8374 | J12: 33496 | K12: 26016 | L12: 7480 | M12: =TEXT(B12,"mmmm") -> June
A13: 1012 | B13: 45783 | C13: Customer 3 | D13: South | E13: Gaming Mouse | F13: Computers | G13: Retail Store | H13: 1 | I13: 10939 | J13: 10939 | K13: 8218 | L13: 2721 | M13: =TEXT(B13,"mmmm") -> May
... A101: 1100 | B101: 45763 | C101: Customer 25 | D101: South | E101: Wireless Earbuds | F101: Electronics | G101: Online | H101: 1 | I101: 15100 | J101: 15100 | K101: 11454 | L101: 3646 | M101: =TEXT(B101,"mmmm") -> April

Sheet Dashboard
A1: 📊Sales Performance Dashboard (Jan - Jun 2025)
B4: =ROUND(SUM(Sales_Data!J2:J101)/100000,1)&"L" -> 27.2L | G4: =COUNTA(Sales_Data!A2:A101) -> 100 | J4: =SUM(Sales_Data!J2:J101)/COUNTA(Sales_Data!A2:A101) -> 27221.64 | O4: =ROUND(SUM(Sales_Data!L2:L101)/SUM(Sales_Data!J2:J101)*100,1)&"%" -> 25.3%
G6: =ROUND(SUM(Sales_Data!K2:K101)/100000,1)&"L" -> 20.3L
B19: Top 5 Best-Selling Products
B21: Product | D21: Sum of Units Sold
B23: Gaming Mouse | D23: 45
B24: Bluetooth Speaker | D24: 43
B25: LED Monitor | D25: 40
B26: Backpack | D26: 38
B27: Phone Case | D27: 36
B28: Grand Total | D28: =SUM(D23:F27) -> 202
